nqs_pycore-0.4.0.dist-info/METADATA
nqs_pycore-0.4.0.dist-info/WHEEL
nqs_pycore/__init__.py
nqs_pycore/nqs_pycore.cp312-win_amd64.pyd
nqs_pycore-0.4.0.dist-info/RECORD
